<?xml version="1.0" encoding="utf-8"?>
<abapGit version="v1.0.0" serializer="LCL_OBJECT_IWPR" serializer_version="v1.0.0">
 <asx:abap xmlns:asx="http://www.sap.com/abapxml" version="1.0">
  <asx:values>
   <_-IWBEP_-I_SBD_AT>
    <_-IWBEP_-I_SBD_AT>
     <PROJECT>ZMM_METERIAL</PROJECT>
     <NODE_UUID>EpFVEf8BHuqnhR68et0FAw==</NODE_UUID>
     <NODE_UUID_PA>EpFVEf8BHuqnhPh9ZsSE4g==</NODE_UUID_PA>
     <PLUGIN_PA>/IWBEP/CORE</PLUGIN_PA>
     <NODE_TYPE_PA>PROJ</NODE_TYPE_PA>
     <NAME>GENERATED_METHODS_RDS</NAME>
     <TYPE>V2_RDS</TYPE>
     <MIME_TYPE>XML</MIME_TYPE>
     <VALUE>PD94bWwgdmVyc2lvbj0iMS4wIiBlbmNvZGluZz0idXRmLTgiPz48YXN4OmFiYXAgdmVyc2lvbj0i
MS4wIiB4bWxuczphc3g9Imh0dHA6Ly93d3cuc2FwLmNvbS9hYmFweG1sIj48YXN4OnZhbHVlcz48
R0VOLz48L2FzeDp2YWx1ZXM+PC9hc3g6YWJhcD4=</VALUE>
    </_-IWBEP_-I_SBD_AT>
   </_-IWBEP_-I_SBD_AT>
   <_-IWBEP_-I_SBD_DS>
    <_-IWBEP_-I_SBD_DS>
     <PROJECT>ZMM_METERIAL</PROJECT>
     <NODE_UUID>EpFVEf8BHuqnhPvZXy9E5A==</NODE_UUID>
     <PARENT_UUID>EpFVEf8BHuqnhPh9ZsTE4g==</PARENT_UUID>
     <NAME>MARA</NAME>
     <DS_TYPE>5</DS_TYPE>
    </_-IWBEP_-I_SBD_DS>
    <_-IWBEP_-I_SBD_DS>
     <PROJECT>ZMM_METERIAL</PROJECT>
     <NODE_UUID>EpFVEf8BHuqnhQ+fc58E/A==</NODE_UUID>
     <PARENT_UUID>EpFVEf8BHuqnhPh9ZsTE4g==</PARENT_UUID>
     <NAME>MARC</NAME>
     <DS_TYPE>5</DS_TYPE>
    </_-IWBEP_-I_SBD_DS>
   </_-IWBEP_-I_SBD_DS>
   <_-IWBEP_-I_SBD_DST>
    <_-IWBEP_-I_SBD_DST>
     <SYLANGU>E</SYLANGU>
     <PROJECT>ZMM_METERIAL</PROJECT>
     <NODE_UUID>EpFVEf8BHuqnhPvZXy9E5A==</NODE_UUID>
    </_-IWBEP_-I_SBD_DST>
    <_-IWBEP_-I_SBD_DST>
     <SYLANGU>E</SYLANGU>
     <PROJECT>ZMM_METERIAL</PROJECT>
     <NODE_UUID>EpFVEf8BHuqnhQ+fc58E/A==</NODE_UUID>
    </_-IWBEP_-I_SBD_DST>
   </_-IWBEP_-I_SBD_DST>
   <_-IWBEP_-I_SBD_GA>
    <_-IWBEP_-I_SBD_GA>
     <PROJECT>ZMM_METERIAL</PROJECT>
     <NODE_UUID>EpFVEf8BHuqnhR68et2lAw==</NODE_UUID>
     <CREATION_USER_ID>YASH15</CREATION_USER_ID>
     <CREATION_TIME>20200522123710.697184</CREATION_TIME>
     <NAME>ZCL_ZMM_METERIAL_MPC</NAME>
     <PGMID>R3TR</PGMID>
     <TROBJ_TYPE>CLAS</TROBJ_TYPE>
     <TROBJ_NAME>ZCL_ZMM_METERIAL_MPC</TROBJ_NAME>
     <GEN_ART_TYPE>MPCB</GEN_ART_TYPE>
    </_-IWBEP_-I_SBD_GA>
    <_-IWBEP_-I_SBD_GA>
     <PROJECT>ZMM_METERIAL</PROJECT>
     <NODE_UUID>EpFVEf8BHuqnhR68et3FAw==</NODE_UUID>
     <CREATION_USER_ID>YASH15</CREATION_USER_ID>
     <CREATION_TIME>20200522123710.697189</CREATION_TIME>
     <NAME>ZCL_ZMM_METERIAL_MPC_EXT</NAME>
     <PGMID>R3TR</PGMID>
     <TROBJ_TYPE>CLAS</TROBJ_TYPE>
     <TROBJ_NAME>ZCL_ZMM_METERIAL_MPC_EXT</TROBJ_NAME>
     <GEN_ART_TYPE>MPCS</GEN_ART_TYPE>
    </_-IWBEP_-I_SBD_GA>
    <_-IWBEP_-I_SBD_GA>
     <PROJECT>ZMM_METERIAL</PROJECT>
     <NODE_UUID>EpFVEf8BHuqnhR68et3lAw==</NODE_UUID>
     <CREATION_USER_ID>YASH15</CREATION_USER_ID>
     <CREATION_TIME>20200522123712.627207</CREATION_TIME>
     <NAME>ZCL_ZMM_METERIAL_DPC</NAME>
     <PGMID>R3TR</PGMID>
     <TROBJ_TYPE>CLAS</TROBJ_TYPE>
     <TROBJ_NAME>ZCL_ZMM_METERIAL_DPC</TROBJ_NAME>
     <GEN_ART_TYPE>DPCB</GEN_ART_TYPE>
    </_-IWBEP_-I_SBD_GA>
    <_-IWBEP_-I_SBD_GA>
     <PROJECT>ZMM_METERIAL</PROJECT>
     <NODE_UUID>EpFVEf8BHuqnhR68et4FAw==</NODE_UUID>
     <CREATION_USER_ID>YASH15</CREATION_USER_ID>
     <CREATION_TIME>20200522123713.322414</CREATION_TIME>
     <NAME>ZCL_ZMM_METERIAL_DPC_EXT</NAME>
     <PGMID>R3TR</PGMID>
     <TROBJ_TYPE>CLAS</TROBJ_TYPE>
     <TROBJ_NAME>ZCL_ZMM_METERIAL_DPC_EXT</TROBJ_NAME>
     <GEN_ART_TYPE>DPCS</GEN_ART_TYPE>
    </_-IWBEP_-I_SBD_GA>
    <_-IWBEP_-I_SBD_GA>
     <PROJECT>ZMM_METERIAL</PROJECT>
     <NODE_UUID>EpFVEf8BHuqnhR68et4lAw==</NODE_UUID>
     <CREATION_USER_ID>YASH15</CREATION_USER_ID>
     <CREATION_TIME>20200522123713.877087</CREATION_TIME>
     <NAME>ZMM_METERIAL_MDL</NAME>
     <PGMID>R3TR</PGMID>
     <TROBJ_TYPE>IWMO</TROBJ_TYPE>
     <TROBJ_NAME>ZMM_METERIAL_MDL</TROBJ_NAME>
     <GEN_ART_TYPE>MDL</GEN_ART_TYPE>
    </_-IWBEP_-I_SBD_GA>
    <_-IWBEP_-I_SBD_GA>
     <PROJECT>ZMM_METERIAL</PROJECT>
     <NODE_UUID>EpFVEf8BHuqnhR68et5FAw==</NODE_UUID>
     <CREATION_USER_ID>YASH15</CREATION_USER_ID>
     <CREATION_TIME>20200522123713.877091</CREATION_TIME>
     <NAME>ZMM_METERIAL_SRV</NAME>
     <PGMID>R3TR</PGMID>
     <TROBJ_TYPE>IWSV</TROBJ_TYPE>
     <TROBJ_NAME>ZMM_METERIAL_SRV</TROBJ_NAME>
     <GEN_ART_TYPE>SRV</GEN_ART_TYPE>
    </_-IWBEP_-I_SBD_GA>
   </_-IWBEP_-I_SBD_GA>
   <_-IWBEP_-I_SBD_GAT>
    <_-IWBEP_-I_SBD_GAT>
     <SYLANGU>E</SYLANGU>
     <PROJECT>ZMM_METERIAL</PROJECT>
     <NODE_UUID>EpFVEf8BHuqnhR68et2lAw==</NODE_UUID>
    </_-IWBEP_-I_SBD_GAT>
    <_-IWBEP_-I_SBD_GAT>
     <SYLANGU>E</SYLANGU>
     <PROJECT>ZMM_METERIAL</PROJECT>
     <NODE_UUID>EpFVEf8BHuqnhR68et3FAw==</NODE_UUID>
    </_-IWBEP_-I_SBD_GAT>
    <_-IWBEP_-I_SBD_GAT>
     <SYLANGU>E</SYLANGU>
     <PROJECT>ZMM_METERIAL</PROJECT>
     <NODE_UUID>EpFVEf8BHuqnhR68et3lAw==</NODE_UUID>
    </_-IWBEP_-I_SBD_GAT>
    <_-IWBEP_-I_SBD_GAT>
     <SYLANGU>E</SYLANGU>
     <PROJECT>ZMM_METERIAL</PROJECT>
     <NODE_UUID>EpFVEf8BHuqnhR68et4FAw==</NODE_UUID>
    </_-IWBEP_-I_SBD_GAT>
    <_-IWBEP_-I_SBD_GAT>
     <SYLANGU>E</SYLANGU>
     <PROJECT>ZMM_METERIAL</PROJECT>
     <NODE_UUID>EpFVEf8BHuqnhR68et4lAw==</NODE_UUID>
    </_-IWBEP_-I_SBD_GAT>
    <_-IWBEP_-I_SBD_GAT>
     <SYLANGU>E</SYLANGU>
     <PROJECT>ZMM_METERIAL</PROJECT>
     <NODE_UUID>EpFVEf8BHuqnhR68et5FAw==</NODE_UUID>
    </_-IWBEP_-I_SBD_GAT>
   </_-IWBEP_-I_SBD_GAT>
   <_-IWBEP_-I_SBD_MD>
    <_-IWBEP_-I_SBD_MD>
     <PROJECT>ZMM_METERIAL</PROJECT>
     <NODE_UUID>EpFVEf8BHuqnhPh9ZsSk4g==</NODE_UUID>
     <NODE_UUID_PA>EpFVEf8BHuqnhPh9ZsSE4g==</NODE_UUID_PA>
     <PLUGIN_PA>/IWBEP/CORE</PLUGIN_PA>
     <NODE_TYPE_PA>PROJ</NODE_TYPE_PA>
     <TECHNICAL_NAME>ZMM_METERIAL_MDL</TECHNICAL_NAME>
     <VERSION>0001</VERSION>
     <MPC>ZCL_ZMM_METERIAL_MPC_EXT</MPC>
     <STATE_NS>S</STATE_NS>
     <VALUE_NS>ZMM_METERIAL_SRV</VALUE_NS>
    </_-IWBEP_-I_SBD_MD>
   </_-IWBEP_-I_SBD_MD>
   <_-IWBEP_-I_SBD_MDT>
    <_-IWBEP_-I_SBD_MDT>
     <SYLANGU>E</SYLANGU>
     <PROJECT>ZMM_METERIAL</PROJECT>
     <NODE_UUID>EpFVEf8BHuqnhPh9ZsSk4g==</NODE_UUID>
    </_-IWBEP_-I_SBD_MDT>
   </_-IWBEP_-I_SBD_MDT>
   <_-IWBEP_-I_SBD_NOI>
    <_-IWBEP_-I_SBD_NOI>
     <PROJECT>ZMM_METERIAL</PROJECT>
     <NODE_UUID>EpFVEf8BHuqnhPh9ZsSE4g==</NODE_UUID>
    </_-IWBEP_-I_SBD_NOI>
    <_-IWBEP_-I_SBD_NOI>
     <PROJECT>ZMM_METERIAL</PROJECT>
     <NODE_UUID>EpFVEf8BHuqnhPh9ZsSk4g==</NODE_UUID>
    </_-IWBEP_-I_SBD_NOI>
    <_-IWBEP_-I_SBD_NOI>
     <PROJECT>ZMM_METERIAL</PROJECT>
     <NODE_UUID>EpFVEf8BHuqnhPh9ZsTE4g==</NODE_UUID>
    </_-IWBEP_-I_SBD_NOI>
    <_-IWBEP_-I_SBD_NOI>
     <PROJECT>ZMM_METERIAL</PROJECT>
     <NODE_UUID>EpFVEf8BHuqnhPvZXy9E5A==</NODE_UUID>
    </_-IWBEP_-I_SBD_NOI>
    <_-IWBEP_-I_SBD_NOI>
     <PROJECT>ZMM_METERIAL</PROJECT>
     <NODE_UUID>EpFVEf8BHuqnhQ1wjizE6w==</NODE_UUID>
     <TYPE>DASO</TYPE>
     <NAME>12915511FF011EEAA784FBD95F2F44E4MARA</NAME>
    </_-IWBEP_-I_SBD_NOI>
    <_-IWBEP_-I_SBD_NOI>
     <PROJECT>ZMM_METERIAL</PROJECT>
     <NODE_UUID>EpFVEf8BHuqnhQ1wjizk6w==</NODE_UUID>
     <TYPE>DASO</TYPE>
     <NAME>12915511FF011EEAA784FBD95F2F44E4MARA\MATNR</NAME>
    </_-IWBEP_-I_SBD_NOI>
    <_-IWBEP_-I_SBD_NOI>
     <PROJECT>ZMM_METERIAL</PROJECT>
     <NODE_UUID>EpFVEf8BHuqnhQ1wji0E6w==</NODE_UUID>
     <TYPE>DASO</TYPE>
     <NAME>12915511FF011EEAA784FBD95F2F44E4MARA\MTART</NAME>
    </_-IWBEP_-I_SBD_NOI>
    <_-IWBEP_-I_SBD_NOI>
     <PROJECT>ZMM_METERIAL</PROJECT>
     <NODE_UUID>EpFVEf8BHuqnhQ1wji0k6w==</NODE_UUID>
     <TYPE>DASO</TYPE>
     <NAME>12915511FF011EEAA784FBD95F2F44E4MARA\MEINS</NAME>
    </_-IWBEP_-I_SBD_NOI>
    <_-IWBEP_-I_SBD_NOI>
     <PROJECT>ZMM_METERIAL</PROJECT>
     <NODE_UUID>EpFVEf8BHuqnhQ1wji1E6w==</NODE_UUID>
     <TYPE>DASO</TYPE>
     <NAME>12915511FF011EEAA784FBD95F2F44E4MARA\BRGEW</NAME>
    </_-IWBEP_-I_SBD_NOI>
    <_-IWBEP_-I_SBD_NOI>
     <PROJECT>ZMM_METERIAL</PROJECT>
     <NODE_UUID>EpFVEf8BHuqnhQ1wji1k6w==</NODE_UUID>
     <TYPE>DASO</TYPE>
     <NAME>12915511FF011EEAA784FBD95F2F44E4MARA\NTGEW</NAME>
    </_-IWBEP_-I_SBD_NOI>
    <_-IWBEP_-I_SBD_NOI>
     <PROJECT>ZMM_METERIAL</PROJECT>
     <NODE_UUID>EpFVEf8BHuqnhQ1wji2E6w==</NODE_UUID>
    </_-IWBEP_-I_SBD_NOI>
    <_-IWBEP_-I_SBD_NOI>
     <PROJECT>ZMM_METERIAL</PROJECT>
     <NODE_UUID>EpFVEf8BHuqnhQ1wji2k6w==</NODE_UUID>
    </_-IWBEP_-I_SBD_NOI>
    <_-IWBEP_-I_SBD_NOI>
     <PROJECT>ZMM_METERIAL</PROJECT>
     <NODE_UUID>EpFVEf8BHuqnhQ1wji3E6w==</NODE_UUID>
    </_-IWBEP_-I_SBD_NOI>
    <_-IWBEP_-I_SBD_NOI>
     <PROJECT>ZMM_METERIAL</PROJECT>
     <NODE_UUID>EpFVEf8BHuqnhQ1wji3k6w==</NODE_UUID>
    </_-IWBEP_-I_SBD_NOI>
    <_-IWBEP_-I_SBD_NOI>
     <PROJECT>ZMM_METERIAL</PROJECT>
     <NODE_UUID>EpFVEf8BHuqnhQ1wji4E6w==</NODE_UUID>
    </_-IWBEP_-I_SBD_NOI>
    <_-IWBEP_-I_SBD_NOI>
     <PROJECT>ZMM_METERIAL</PROJECT>
     <NODE_UUID>EpFVEf8BHuqnhQ1wji4k6w==</NODE_UUID>
    </_-IWBEP_-I_SBD_NOI>
    <_-IWBEP_-I_SBD_NOI>
     <PROJECT>ZMM_METERIAL</PROJECT>
     <NODE_UUID>EpFVEf8BHuqnhQ1wji5E6w==</NODE_UUID>
    </_-IWBEP_-I_SBD_NOI>
    <_-IWBEP_-I_SBD_NOI>
     <PROJECT>ZMM_METERIAL</PROJECT>
     <NODE_UUID>EpFVEf8BHuqnhQ+fc58E/A==</NODE_UUID>
    </_-IWBEP_-I_SBD_NOI>
    <_-IWBEP_-I_SBD_NOI>
     <PROJECT>ZMM_METERIAL</PROJECT>
     <NODE_UUID>EpFVEf8BHuqnhRPTmM9E/w==</NODE_UUID>
     <TYPE>DASO</TYPE>
     <NAME>12915511FF011EEAA7850F9F739F04FCMARC</NAME>
    </_-IWBEP_-I_SBD_NOI>
    <_-IWBEP_-I_SBD_NOI>
     <PROJECT>ZMM_METERIAL</PROJECT>
     <NODE_UUID>EpFVEf8BHuqnhRPTmM9k/w==</NODE_UUID>
     <TYPE>DASO</TYPE>
     <NAME>12915511FF011EEAA7850F9F739F04FCMARC\MATNR</NAME>
    </_-IWBEP_-I_SBD_NOI>
    <_-IWBEP_-I_SBD_NOI>
     <PROJECT>ZMM_METERIAL</PROJECT>
     <NODE_UUID>EpFVEf8BHuqnhRPTmM+E/w==</NODE_UUID>
     <TYPE>DASO</TYPE>
     <NAME>12915511FF011EEAA7850F9F739F04FCMARC\WERKS</NAME>
    </_-IWBEP_-I_SBD_NOI>
    <_-IWBEP_-I_SBD_NOI>
     <PROJECT>ZMM_METERIAL</PROJECT>
     <NODE_UUID>EpFVEf8BHuqnhRPTmM+k/w==</NODE_UUID>
     <TYPE>DASO</TYPE>
     <NAME>12915511FF011EEAA7850F9F739F04FCMARC\EKGRP</NAME>
    </_-IWBEP_-I_SBD_NOI>
    <_-IWBEP_-I_SBD_NOI>
     <PROJECT>ZMM_METERIAL</PROJECT>
     <NODE_UUID>EpFVEf8BHuqnhRPTmM/E/w==</NODE_UUID>
    </_-IWBEP_-I_SBD_NOI>
    <_-IWBEP_-I_SBD_NOI>
     <PROJECT>ZMM_METERIAL</PROJECT>
     <NODE_UUID>EpFVEf8BHuqnhRPTmM/k/w==</NODE_UUID>
    </_-IWBEP_-I_SBD_NOI>
    <_-IWBEP_-I_SBD_NOI>
     <PROJECT>ZMM_METERIAL</PROJECT>
     <NODE_UUID>EpFVEf8BHuqnhRPTmNAE/w==</NODE_UUID>
    </_-IWBEP_-I_SBD_NOI>
    <_-IWBEP_-I_SBD_NOI>
     <PROJECT>ZMM_METERIAL</PROJECT>
     <NODE_UUID>EpFVEf8BHuqnhRPTmNAk/w==</NODE_UUID>
    </_-IWBEP_-I_SBD_NOI>
    <_-IWBEP_-I_SBD_NOI>
     <PROJECT>ZMM_METERIAL</PROJECT>
     <NODE_UUID>EpFVEf8BHuqnhRPTmNBE/w==</NODE_UUID>
    </_-IWBEP_-I_SBD_NOI>
    <_-IWBEP_-I_SBD_NOI>
     <PROJECT>ZMM_METERIAL</PROJECT>
     <NODE_UUID>EpFVEf8BHuqnhRPTmNBk/w==</NODE_UUID>
    </_-IWBEP_-I_SBD_NOI>
    <_-IWBEP_-I_SBD_NOI>
     <PROJECT>ZMM_METERIAL</PROJECT>
     <NODE_UUID>EpFVEf8BHuqnhRPTmNCE/w==</NODE_UUID>
    </_-IWBEP_-I_SBD_NOI>
    <_-IWBEP_-I_SBD_NOI>
     <PROJECT>ZMM_METERIAL</PROJECT>
     <NODE_UUID>EpFVEf8BHuqnhRskqCtFAw==</NODE_UUID>
    </_-IWBEP_-I_SBD_NOI>
    <_-IWBEP_-I_SBD_NOI>
     <PROJECT>ZMM_METERIAL</PROJECT>
     <NODE_UUID>EpFVEf8BHuqnhRskqCtlAw==</NODE_UUID>
    </_-IWBEP_-I_SBD_NOI>
    <_-IWBEP_-I_SBD_NOI>
     <PROJECT>ZMM_METERIAL</PROJECT>
     <NODE_UUID>EpFVEf8BHuqnhRskqCuFAw==</NODE_UUID>
    </_-IWBEP_-I_SBD_NOI>
    <_-IWBEP_-I_SBD_NOI>
     <PROJECT>ZMM_METERIAL</PROJECT>
     <NODE_UUID>EpFVEf8BHuqnhRyNYcPFAw==</NODE_UUID>
    </_-IWBEP_-I_SBD_NOI>
    <_-IWBEP_-I_SBD_NOI>
     <PROJECT>ZMM_METERIAL</PROJECT>
     <NODE_UUID>EpFVEf8BHuqnhR68et0FAw==</NODE_UUID>
    </_-IWBEP_-I_SBD_NOI>
    <_-IWBEP_-I_SBD_NOI>
     <PROJECT>ZMM_METERIAL</PROJECT>
     <NODE_UUID>EpFVEf8BHuqnhR68et2lAw==</NODE_UUID>
    </_-IWBEP_-I_SBD_NOI>
    <_-IWBEP_-I_SBD_NOI>
     <PROJECT>ZMM_METERIAL</PROJECT>
     <NODE_UUID>EpFVEf8BHuqnhR68et3FAw==</NODE_UUID>
    </_-IWBEP_-I_SBD_NOI>
    <_-IWBEP_-I_SBD_NOI>
     <PROJECT>ZMM_METERIAL</PROJECT>
     <NODE_UUID>EpFVEf8BHuqnhR68et3lAw==</NODE_UUID>
    </_-IWBEP_-I_SBD_NOI>
    <_-IWBEP_-I_SBD_NOI>
     <PROJECT>ZMM_METERIAL</PROJECT>
     <NODE_UUID>EpFVEf8BHuqnhR68et4FAw==</NODE_UUID>
    </_-IWBEP_-I_SBD_NOI>
    <_-IWBEP_-I_SBD_NOI>
     <PROJECT>ZMM_METERIAL</PROJECT>
     <NODE_UUID>EpFVEf8BHuqnhR68et4lAw==</NODE_UUID>
    </_-IWBEP_-I_SBD_NOI>
    <_-IWBEP_-I_SBD_NOI>
     <PROJECT>ZMM_METERIAL</PROJECT>
     <NODE_UUID>EpFVEf8BHuqnhR68et5FAw==</NODE_UUID>
    </_-IWBEP_-I_SBD_NOI>
   </_-IWBEP_-I_SBD_NOI>
   <_-IWBEP_-I_SBD_OP>
    <_-IWBEP_-I_SBD_OP>
     <PROJECT>ZMM_METERIAL</PROJECT>
     <NODE_UUID>EpFVEf8BHuqnhQ1wji3E6w==</NODE_UUID>
     <PARENT_UUID>EpFVEf8BHuqnhQ1wji2k6w==</PARENT_UUID>
     <NAME>Create</NAME>
     <OPERATION_TYPE>C</OPERATION_TYPE>
     <IMP_METHOD>MATERIALSET_CREATE_ENTITY</IMP_METHOD>
    </_-IWBEP_-I_SBD_OP>
    <_-IWBEP_-I_SBD_OP>
     <PROJECT>ZMM_METERIAL</PROJECT>
     <NODE_UUID>EpFVEf8BHuqnhQ1wji3k6w==</NODE_UUID>
     <PARENT_UUID>EpFVEf8BHuqnhQ1wji2k6w==</PARENT_UUID>
     <NAME>GetEntity (Read)</NAME>
     <OPERATION_TYPE>R</OPERATION_TYPE>
     <IMP_METHOD>MATERIALSET_GET_ENTITY</IMP_METHOD>
    </_-IWBEP_-I_SBD_OP>
    <_-IWBEP_-I_SBD_OP>
     <PROJECT>ZMM_METERIAL</PROJECT>
     <NODE_UUID>EpFVEf8BHuqnhQ1wji4E6w==</NODE_UUID>
     <PARENT_UUID>EpFVEf8BHuqnhQ1wji2k6w==</PARENT_UUID>
     <NAME>Update</NAME>
     <OPERATION_TYPE>U</OPERATION_TYPE>
     <IMP_METHOD>MATERIALSET_UPDATE_ENTITY</IMP_METHOD>
    </_-IWBEP_-I_SBD_OP>
    <_-IWBEP_-I_SBD_OP>
     <PROJECT>ZMM_METERIAL</PROJECT>
     <NODE_UUID>EpFVEf8BHuqnhQ1wji4k6w==</NODE_UUID>
     <PARENT_UUID>EpFVEf8BHuqnhQ1wji2k6w==</PARENT_UUID>
     <NAME>Delete</NAME>
     <OPERATION_TYPE>D</OPERATION_TYPE>
     <IMP_METHOD>MATERIALSET_DELETE_ENTITY</IMP_METHOD>
    </_-IWBEP_-I_SBD_OP>
    <_-IWBEP_-I_SBD_OP>
     <PROJECT>ZMM_METERIAL</PROJECT>
     <NODE_UUID>EpFVEf8BHuqnhQ1wji5E6w==</NODE_UUID>
     <PARENT_UUID>EpFVEf8BHuqnhQ1wji2k6w==</PARENT_UUID>
     <NAME>GetEntitySet (Query)</NAME>
     <OPERATION_TYPE>Q</OPERATION_TYPE>
     <IMP_METHOD>MATERIALSET_GET_ENTITYSET</IMP_METHOD>
    </_-IWBEP_-I_SBD_OP>
    <_-IWBEP_-I_SBD_OP>
     <PROJECT>ZMM_METERIAL</PROJECT>
     <NODE_UUID>EpFVEf8BHuqnhRPTmNAE/w==</NODE_UUID>
     <PARENT_UUID>EpFVEf8BHuqnhRPTmM/k/w==</PARENT_UUID>
     <NAME>Create</NAME>
     <OPERATION_TYPE>C</OPERATION_TYPE>
     <IMP_METHOD>PLANTSET_CREATE_ENTITY</IMP_METHOD>
    </_-IWBEP_-I_SBD_OP>
    <_-IWBEP_-I_SBD_OP>
     <PROJECT>ZMM_METERIAL</PROJECT>
     <NODE_UUID>EpFVEf8BHuqnhRPTmNAk/w==</NODE_UUID>
     <PARENT_UUID>EpFVEf8BHuqnhRPTmM/k/w==</PARENT_UUID>
     <NAME>GetEntity (Read)</NAME>
     <OPERATION_TYPE>R</OPERATION_TYPE>
     <IMP_METHOD>PLANTSET_GET_ENTITY</IMP_METHOD>
    </_-IWBEP_-I_SBD_OP>
    <_-IWBEP_-I_SBD_OP>
     <PROJECT>ZMM_METERIAL</PROJECT>
     <NODE_UUID>EpFVEf8BHuqnhRPTmNBE/w==</NODE_UUID>
     <PARENT_UUID>EpFVEf8BHuqnhRPTmM/k/w==</PARENT_UUID>
     <NAME>Update</NAME>
     <OPERATION_TYPE>U</OPERATION_TYPE>
     <IMP_METHOD>PLANTSET_UPDATE_ENTITY</IMP_METHOD>
    </_-IWBEP_-I_SBD_OP>
    <_-IWBEP_-I_SBD_OP>
     <PROJECT>ZMM_METERIAL</PROJECT>
     <NODE_UUID>EpFVEf8BHuqnhRPTmNBk/w==</NODE_UUID>
     <PARENT_UUID>EpFVEf8BHuqnhRPTmM/k/w==</PARENT_UUID>
     <NAME>Delete</NAME>
     <OPERATION_TYPE>D</OPERATION_TYPE>
     <IMP_METHOD>PLANTSET_DELETE_ENTITY</IMP_METHOD>
    </_-IWBEP_-I_SBD_OP>
    <_-IWBEP_-I_SBD_OP>
     <PROJECT>ZMM_METERIAL</PROJECT>
     <NODE_UUID>EpFVEf8BHuqnhRPTmNCE/w==</NODE_UUID>
     <PARENT_UUID>EpFVEf8BHuqnhRPTmM/k/w==</PARENT_UUID>
     <NAME>GetEntitySet (Query)</NAME>
     <OPERATION_TYPE>Q</OPERATION_TYPE>
     <IMP_METHOD>PLANTSET_GET_ENTITYSET</IMP_METHOD>
    </_-IWBEP_-I_SBD_OP>
   </_-IWBEP_-I_SBD_OP>
   <_-IWBEP_-I_SBD_OPT>
    <_-IWBEP_-I_SBD_OPT>
     <SYLANGU>E</SYLANGU>
     <PROJECT>ZMM_METERIAL</PROJECT>
     <NODE_UUID>EpFVEf8BHuqnhQ1wji3E6w==</NODE_UUID>
    </_-IWBEP_-I_SBD_OPT>
    <_-IWBEP_-I_SBD_OPT>
     <SYLANGU>E</SYLANGU>
     <PROJECT>ZMM_METERIAL</PROJECT>
     <NODE_UUID>EpFVEf8BHuqnhQ1wji3k6w==</NODE_UUID>
    </_-IWBEP_-I_SBD_OPT>
    <_-IWBEP_-I_SBD_OPT>
     <SYLANGU>E</SYLANGU>
     <PROJECT>ZMM_METERIAL</PROJECT>
     <NODE_UUID>EpFVEf8BHuqnhQ1wji4E6w==</NODE_UUID>
    </_-IWBEP_-I_SBD_OPT>
    <_-IWBEP_-I_SBD_OPT>
     <SYLANGU>E</SYLANGU>
     <PROJECT>ZMM_METERIAL</PROJECT>
     <NODE_UUID>EpFVEf8BHuqnhQ1wji4k6w==</NODE_UUID>
    </_-IWBEP_-I_SBD_OPT>
    <_-IWBEP_-I_SBD_OPT>
     <SYLANGU>E</SYLANGU>
     <PROJECT>ZMM_METERIAL</PROJECT>
     <NODE_UUID>EpFVEf8BHuqnhQ1wji5E6w==</NODE_UUID>
    </_-IWBEP_-I_SBD_OPT>
    <_-IWBEP_-I_SBD_OPT>
     <SYLANGU>E</SYLANGU>
     <PROJECT>ZMM_METERIAL</PROJECT>
     <NODE_UUID>EpFVEf8BHuqnhRPTmNAE/w==</NODE_UUID>
    </_-IWBEP_-I_SBD_OPT>
    <_-IWBEP_-I_SBD_OPT>
     <SYLANGU>E</SYLANGU>
     <PROJECT>ZMM_METERIAL</PROJECT>
     <NODE_UUID>EpFVEf8BHuqnhRPTmNAk/w==</NODE_UUID>
    </_-IWBEP_-I_SBD_OPT>
    <_-IWBEP_-I_SBD_OPT>
     <SYLANGU>E</SYLANGU>
     <PROJECT>ZMM_METERIAL</PROJECT>
     <NODE_UUID>EpFVEf8BHuqnhRPTmNBE/w==</NODE_UUID>
    </_-IWBEP_-I_SBD_OPT>
    <_-IWBEP_-I_SBD_OPT>
     <SYLANGU>E</SYLANGU>
     <PROJECT>ZMM_METERIAL</PROJECT>
     <NODE_UUID>EpFVEf8BHuqnhRPTmNBk/w==</NODE_UUID>
    </_-IWBEP_-I_SBD_OPT>
    <_-IWBEP_-I_SBD_OPT>
     <SYLANGU>E</SYLANGU>
     <PROJECT>ZMM_METERIAL</PROJECT>
     <NODE_UUID>EpFVEf8BHuqnhRPTmNCE/w==</NODE_UUID>
    </_-IWBEP_-I_SBD_OPT>
   </_-IWBEP_-I_SBD_OPT>
   <_-IWBEP_-I_SBD_PR>
    <_-IWBEP_-I_SBD_PR>
     <PROJECT>ZMM_METERIAL</PROJECT>
     <NODE_UUID>EpFVEf8BHuqnhPh9ZsSE4g==</NODE_UUID>
     <CREATION_USER_ID>YASH15</CREATION_USER_ID>
     <CREATION_TIME>20200522122839.285313</CREATION_TIME>
     <LAST_CHG_USER_ID>YASH15</LAST_CHG_USER_ID>
     <LAST_CHG_TIME>20200522123713.878964</LAST_CHG_TIME>
     <LAST_CHG_STATE>EpFVEf8BHuqnhR68et5lAw==</LAST_CHG_STATE>
     <PLUGIN>/IWBEP/GEN</PLUGIN>
     <STRAT_NAME>0001</STRAT_NAME>
     <STRAT_VERSION>0001</STRAT_VERSION>
     <PROJECT_TYPE>1</PROJECT_TYPE>
    </_-IWBEP_-I_SBD_PR>
   </_-IWBEP_-I_SBD_PR>
   <_-IWBEP_-I_SBD_PRT>
    <_-IWBEP_-I_SBD_PRT>
     <PROJECT>ZMM_METERIAL</PROJECT>
     <SYLANGU>E</SYLANGU>
     <DESCRIPTION>Material List</DESCRIPTION>
    </_-IWBEP_-I_SBD_PRT>
   </_-IWBEP_-I_SBD_PRT>
   <_-IWBEP_-I_SBD_SE>
    <_-IWBEP_-I_SBD_SE>
     <PROJECT>ZMM_METERIAL</PROJECT>
     <NODE_UUID>EpFVEf8BHuqnhQ1wji2k6w==</NODE_UUID>
     <PARENT_UUID>EpFVEf8BHuqnhPh9ZsTE4g==</PARENT_UUID>
     <NAME>MaterialSet</NAME>
     <ENTITY_SET_UUID>EpFVEf8BHuqnhQ1wji2E6w==</ENTITY_SET_UUID>
    </_-IWBEP_-I_SBD_SE>
    <_-IWBEP_-I_SBD_SE>
     <PROJECT>ZMM_METERIAL</PROJECT>
     <NODE_UUID>EpFVEf8BHuqnhRPTmM/k/w==</NODE_UUID>
     <PARENT_UUID>EpFVEf8BHuqnhPh9ZsTE4g==</PARENT_UUID>
     <NAME>PlantSet</NAME>
     <ENTITY_SET_UUID>EpFVEf8BHuqnhRPTmM/E/w==</ENTITY_SET_UUID>
    </_-IWBEP_-I_SBD_SE>
   </_-IWBEP_-I_SBD_SE>
   <_-IWBEP_-I_SBD_SET>
    <_-IWBEP_-I_SBD_SET>
     <SYLANGU>E</SYLANGU>
     <PROJECT>ZMM_METERIAL</PROJECT>
     <NODE_UUID>EpFVEf8BHuqnhQ1wji2k6w==</NODE_UUID>
    </_-IWBEP_-I_SBD_SET>
    <_-IWBEP_-I_SBD_SET>
     <SYLANGU>E</SYLANGU>
     <PROJECT>ZMM_METERIAL</PROJECT>
     <NODE_UUID>EpFVEf8BHuqnhRPTmM/k/w==</NODE_UUID>
    </_-IWBEP_-I_SBD_SET>
   </_-IWBEP_-I_SBD_SET>
   <_-IWBEP_-I_SBD_SV>
    <_-IWBEP_-I_SBD_SV>
     <PROJECT>ZMM_METERIAL</PROJECT>
     <NODE_UUID>EpFVEf8BHuqnhPh9ZsTE4g==</NODE_UUID>
     <TECHNICAL_NAME>ZMM_METERIAL_SRV</TECHNICAL_NAME>
     <VERSION>0001</VERSION>
     <DPC>ZCL_ZMM_METERIAL_DPC_EXT</DPC>
     <EXTERNAL_NAME>ZMM_METERIAL_SRV</EXTERNAL_NAME>
    </_-IWBEP_-I_SBD_SV>
   </_-IWBEP_-I_SBD_SV>
   <_-IWBEP_-I_SBD_SVT>
    <_-IWBEP_-I_SBD_SVT>
     <SYLANGU>E</SYLANGU>
     <PROJECT>ZMM_METERIAL</PROJECT>
     <NODE_UUID>EpFVEf8BHuqnhPh9ZsTE4g==</NODE_UUID>
    </_-IWBEP_-I_SBD_SVT>
   </_-IWBEP_-I_SBD_SVT>
   <_-IWBEP_-I_SBO_ASO>
    <_-IWBEP_-I_SBO_ASO>
     <PROJECT>ZMM_METERIAL</PROJECT>
     <NODE_UUID>EpFVEf8BHuqnhRskqCtFAw==</NODE_UUID>
     <NAME>MatToPlant</NAME>
     <MODEL_GUID>EpFVEf8BHuqnhPh9ZsSk4g==</MODEL_GUID>
     <LEFT_END_GUID>EpFVEf8BHuqnhQ1wjizE6w==</LEFT_END_GUID>
     <RIGHT_END_GUID>EpFVEf8BHuqnhRPTmM9E/w==</RIGHT_END_GUID>
     <LEFT_END_CARD>N</LEFT_END_CARD>
     <RIGHT_END_CARD>M</RIGHT_END_CARD>
     <REF_TYPE>T</REF_TYPE>
     <TXTR_XU>X</TXTR_XU>
     <DESCRIPTION_XU>X</DESCRIPTION_XU>
     <ASSOC_LABEL_XU>X</ASSOC_LABEL_XU>
    </_-IWBEP_-I_SBO_ASO>
   </_-IWBEP_-I_SBO_ASO>
   <_-IWBEP_-I_SBO_AST>
    <_-IWBEP_-I_SBO_AST>
     <SYLANGU>E</SYLANGU>
     <PROJECT>ZMM_METERIAL</PROJECT>
     <NODE_UUID>EpFVEf8BHuqnhRskqCtFAw==</NODE_UUID>
    </_-IWBEP_-I_SBO_AST>
   </_-IWBEP_-I_SBO_AST>
   <_-IWBEP_-I_SBO_AT>
    <_-IWBEP_-I_SBO_AT>
     <PROJECT>ZMM_METERIAL</PROJECT>
     <NODE_UUID>EpFVEf8BHuqnhRyNYcPFAw==</NODE_UUID>
     <NAME>MatToPlantSet</NAME>
     <MODEL_GUID>EpFVEf8BHuqnhPh9ZsSk4g==</MODEL_GUID>
     <LEFT_END_GUID>EpFVEf8BHuqnhQ1wji2E6w==</LEFT_END_GUID>
     <RIGHT_END_GUID>EpFVEf8BHuqnhRPTmM/E/w==</RIGHT_END_GUID>
     <ASSOCIATION_GUID>EpFVEf8BHuqnhRskqCtFAw==</ASSOCIATION_GUID>
     <REF_TYPE>T</REF_TYPE>
     <TXTR_XU>X</TXTR_XU>
     <DESCRIPTION_XU>X</DESCRIPTION_XU>
     <ASST_LABEL_XU>X</ASST_LABEL_XU>
    </_-IWBEP_-I_SBO_AT>
   </_-IWBEP_-I_SBO_AT>
   <_-IWBEP_-I_SBO_ATT>
    <_-IWBEP_-I_SBO_ATT>
     <SYLANGU>E</SYLANGU>
     <PROJECT>ZMM_METERIAL</PROJECT>
     <NODE_UUID>EpFVEf8BHuqnhRyNYcPFAw==</NODE_UUID>
    </_-IWBEP_-I_SBO_ATT>
   </_-IWBEP_-I_SBO_ATT>
   <_-IWBEP_-I_SBO_ES>
    <_-IWBEP_-I_SBO_ES>
     <PROJECT>ZMM_METERIAL</PROJECT>
     <NODE_UUID>EpFVEf8BHuqnhQ1wji2E6w==</NODE_UUID>
     <MODEL>EpFVEf8BHuqnhPh9ZsSk4g==</MODEL>
     <NAME>MaterialSet</NAME>
     <ENTITY_TYPE>EpFVEf8BHuqnhQ1wjizE6w==</ENTITY_TYPE>
     <ADDRESSABLE>X</ADDRESSABLE>
     <REF_TYPE>T</REF_TYPE>
     <TECH_NAME>MATERIALSET</TECH_NAME>
     <CREATABLE_XU>X</CREATABLE_XU>
     <UPDATABLE_XU>X</UPDATABLE_XU>
     <DELETABLE_XU>X</DELETABLE_XU>
     <PAGEABLE_XU>X</PAGEABLE_XU>
     <SEARCHABLE_XU>X</SEARCHABLE_XU>
     <SUBSCRIBABLE_XU>X</SUBSCRIBABLE_XU>
     <REQUIRES_FLT_XU>X</REQUIRES_FLT_XU>
     <SEMANTIC_XU>X</SEMANTIC_XU>
     <LABEL_REF_XU>X</LABEL_REF_XU>
     <DESCRIPTION_XU>X</DESCRIPTION_XU>
     <ESET_LABEL_XU>X</ESET_LABEL_XU>
     <IN_SERV_DOCU>X</IN_SERV_DOCU>
    </_-IWBEP_-I_SBO_ES>
    <_-IWBEP_-I_SBO_ES>
     <PROJECT>ZMM_METERIAL</PROJECT>
     <NODE_UUID>EpFVEf8BHuqnhRPTmM/E/w==</NODE_UUID>
     <MODEL>EpFVEf8BHuqnhPh9ZsSk4g==</MODEL>
     <NAME>PlantSet</NAME>
     <ENTITY_TYPE>EpFVEf8BHuqnhRPTmM9E/w==</ENTITY_TYPE>
     <ADDRESSABLE>X</ADDRESSABLE>
     <REF_TYPE>T</REF_TYPE>
     <TECH_NAME>PLANTSET</TECH_NAME>
     <CREATABLE_XU>X</CREATABLE_XU>
     <UPDATABLE_XU>X</UPDATABLE_XU>
     <DELETABLE_XU>X</DELETABLE_XU>
     <PAGEABLE_XU>X</PAGEABLE_XU>
     <SEARCHABLE_XU>X</SEARCHABLE_XU>
     <SUBSCRIBABLE_XU>X</SUBSCRIBABLE_XU>
     <REQUIRES_FLT_XU>X</REQUIRES_FLT_XU>
     <SEMANTIC_XU>X</SEMANTIC_XU>
     <LABEL_REF_XU>X</LABEL_REF_XU>
     <DESCRIPTION_XU>X</DESCRIPTION_XU>
     <ESET_LABEL_XU>X</ESET_LABEL_XU>
     <IN_SERV_DOCU>X</IN_SERV_DOCU>
    </_-IWBEP_-I_SBO_ES>
   </_-IWBEP_-I_SBO_ES>
   <_-IWBEP_-I_SBO_EST>
    <_-IWBEP_-I_SBO_EST>
     <SYLANGU>E</SYLANGU>
     <PROJECT>ZMM_METERIAL</PROJECT>
     <NODE_UUID>EpFVEf8BHuqnhQ1wji2E6w==</NODE_UUID>
    </_-IWBEP_-I_SBO_EST>
    <_-IWBEP_-I_SBO_EST>
     <SYLANGU>E</SYLANGU>
     <PROJECT>ZMM_METERIAL</PROJECT>
     <NODE_UUID>EpFVEf8BHuqnhRPTmM/E/w==</NODE_UUID>
    </_-IWBEP_-I_SBO_EST>
   </_-IWBEP_-I_SBO_EST>
   <_-IWBEP_-I_SBO_ET>
    <_-IWBEP_-I_SBO_ET>
     <PROJECT>ZMM_METERIAL</PROJECT>
     <NODE_UUID>EpFVEf8BHuqnhQ1wjizE6w==</NODE_UUID>
     <NAME>Material</NAME>
     <MODEL>EpFVEf8BHuqnhPh9ZsSk4g==</MODEL>
     <REF_TYPE>T</REF_TYPE>
     <ABAP_STRUCT>MARA</ABAP_STRUCT>
     <TECH_NAME>MATERIAL</TECH_NAME>
     <BASE_TYPE_XU>X</BASE_TYPE_XU>
     <FC_TARGET_PATHXU>X</FC_TARGET_PATHXU>
     <TXTR_XU>X</TXTR_XU>
     <DESCRIPTION_XU>X</DESCRIPTION_XU>
     <ET_LABEL_XU>X</ET_LABEL_XU>
    </_-IWBEP_-I_SBO_ET>
    <_-IWBEP_-I_SBO_ET>
     <PROJECT>ZMM_METERIAL</PROJECT>
     <NODE_UUID>EpFVEf8BHuqnhRPTmM9E/w==</NODE_UUID>
     <NAME>Plant</NAME>
     <MODEL>EpFVEf8BHuqnhPh9ZsSk4g==</MODEL>
     <REF_TYPE>T</REF_TYPE>
     <ABAP_STRUCT>MARC</ABAP_STRUCT>
     <TECH_NAME>PLANT</TECH_NAME>
     <BASE_TYPE_XU>X</BASE_TYPE_XU>
     <FC_TARGET_PATHXU>X</FC_TARGET_PATHXU>
     <TXTR_XU>X</TXTR_XU>
     <DESCRIPTION_XU>X</DESCRIPTION_XU>
     <ET_LABEL_XU>X</ET_LABEL_XU>
    </_-IWBEP_-I_SBO_ET>
   </_-IWBEP_-I_SBO_ET>
   <_-IWBEP_-I_SBO_ETT>
    <_-IWBEP_-I_SBO_ETT>
     <SYLANGU>E</SYLANGU>
     <PROJECT>ZMM_METERIAL</PROJECT>
     <NODE_UUID>EpFVEf8BHuqnhQ1wjizE6w==</NODE_UUID>
    </_-IWBEP_-I_SBO_ETT>
    <_-IWBEP_-I_SBO_ETT>
     <SYLANGU>E</SYLANGU>
     <PROJECT>ZMM_METERIAL</PROJECT>
     <NODE_UUID>EpFVEf8BHuqnhRPTmM9E/w==</NODE_UUID>
    </_-IWBEP_-I_SBO_ETT>
   </_-IWBEP_-I_SBO_ETT>
   <_-IWBEP_-I_SBO_NP>
    <_-IWBEP_-I_SBO_NP>
     <PROJECT>ZMM_METERIAL</PROJECT>
     <NODE_UUID>EpFVEf8BHuqnhRskqCtlAw==</NODE_UUID>
     <NAME>MtoP</NAME>
     <RELATION_GUID>EpFVEf8BHuqnhRskqCtFAw==</RELATION_GUID>
     <ENTITY_GUID>EpFVEf8BHuqnhQ1wjizE6w==</ENTITY_GUID>
     <REF_TYPE>T</REF_TYPE>
     <TECH_NAME>MTOP</TECH_NAME>
     <FROM_ROLE_XU>X</FROM_ROLE_XU>
     <TO_ROLE_XU>X</TO_ROLE_XU>
     <TXTR_XU>X</TXTR_XU>
     <DESCRIPTION_XU>X</DESCRIPTION_XU>
     <NAVP_LABEL_XU>X</NAVP_LABEL_XU>
    </_-IWBEP_-I_SBO_NP>
   </_-IWBEP_-I_SBO_NP>
   <_-IWBEP_-I_SBO_NPT>
    <_-IWBEP_-I_SBO_NPT>
     <SYLANGU>E</SYLANGU>
     <PROJECT>ZMM_METERIAL</PROJECT>
     <NODE_UUID>EpFVEf8BHuqnhRskqCtlAw==</NODE_UUID>
    </_-IWBEP_-I_SBO_NPT>
   </_-IWBEP_-I_SBO_NPT>
   <_-IWBEP_-I_SBO_PR>
    <_-IWBEP_-I_SBO_PR>
     <PROJECT>ZMM_METERIAL</PROJECT>
     <NODE_UUID>EpFVEf8BHuqnhQ1wjizk6w==</NODE_UUID>
     <PARENT_UUID>EpFVEf8BHuqnhQ1wjizE6w==</PARENT_UUID>
     <NAME>Matnr</NAME>
     <IS_KEY>X</IS_KEY>
     <MAX_LENGTH>40</MAX_LENGTH>
     <EDM_CORE_TYPE>Edm.String</EDM_CORE_TYPE>
     <REF_TYPE>T</REF_TYPE>
     <ABAP_FIELD>MATNR</ABAP_FIELD>
     <AS_ETAG_XU>X</AS_ETAG_XU>
     <REQUIREFILTER_XU>X</REQUIREFILTER_XU>
     <UNIT_PROP_XU>X</UNIT_PROP_XU>
     <ABTY_XU>X</ABTY_XU>
     <SORT_ORDER>1</SORT_ORDER>
     <DESCRIPTION_XU>X</DESCRIPTION_XU>
    </_-IWBEP_-I_SBO_PR>
    <_-IWBEP_-I_SBO_PR>
     <PROJECT>ZMM_METERIAL</PROJECT>
     <NODE_UUID>EpFVEf8BHuqnhQ1wji0E6w==</NODE_UUID>
     <PARENT_UUID>EpFVEf8BHuqnhQ1wjizE6w==</PARENT_UUID>
     <NAME>Mtart</NAME>
     <MAX_LENGTH>4</MAX_LENGTH>
     <EDM_CORE_TYPE>Edm.String</EDM_CORE_TYPE>
     <REF_TYPE>T</REF_TYPE>
     <ABAP_FIELD>MTART</ABAP_FIELD>
     <AS_ETAG_XU>X</AS_ETAG_XU>
     <REQUIREFILTER_XU>X</REQUIREFILTER_XU>
     <UNIT_PROP_XU>X</UNIT_PROP_XU>
     <ABTY_XU>X</ABTY_XU>
     <SORT_ORDER>2</SORT_ORDER>
     <DESCRIPTION_XU>X</DESCRIPTION_XU>
    </_-IWBEP_-I_SBO_PR>
    <_-IWBEP_-I_SBO_PR>
     <PROJECT>ZMM_METERIAL</PROJECT>
     <NODE_UUID>EpFVEf8BHuqnhQ1wji0k6w==</NODE_UUID>
     <PARENT_UUID>EpFVEf8BHuqnhQ1wjizE6w==</PARENT_UUID>
     <NAME>Meins</NAME>
     <MAX_LENGTH>3</MAX_LENGTH>
     <EDM_CORE_TYPE>Edm.String</EDM_CORE_TYPE>
     <REF_TYPE>T</REF_TYPE>
     <ABAP_FIELD>MEINS</ABAP_FIELD>
     <AS_ETAG_XU>X</AS_ETAG_XU>
     <REQUIREFILTER_XU>X</REQUIREFILTER_XU>
     <UNIT_PROP_XU>X</UNIT_PROP_XU>
     <ABTY_XU>X</ABTY_XU>
     <SORT_ORDER>3</SORT_ORDER>
     <DESCRIPTION_XU>X</DESCRIPTION_XU>
    </_-IWBEP_-I_SBO_PR>
    <_-IWBEP_-I_SBO_PR>
     <PROJECT>ZMM_METERIAL</PROJECT>
     <NODE_UUID>EpFVEf8BHuqnhQ1wji1E6w==</NODE_UUID>
     <PARENT_UUID>EpFVEf8BHuqnhQ1wjizE6w==</PARENT_UUID>
     <NAME>Brgew</NAME>
     <PROP_PRECISION>13</PROP_PRECISION>
     <SCALE>3</SCALE>
     <EDM_CORE_TYPE>Edm.Decimal</EDM_CORE_TYPE>
     <REF_TYPE>T</REF_TYPE>
     <ABAP_FIELD>BRGEW</ABAP_FIELD>
     <AS_ETAG_XU>X</AS_ETAG_XU>
     <REQUIREFILTER_XU>X</REQUIREFILTER_XU>
     <UNIT_PROP_XU>X</UNIT_PROP_XU>
     <ABTY_XU>X</ABTY_XU>
     <SORT_ORDER>4</SORT_ORDER>
     <DESCRIPTION_XU>X</DESCRIPTION_XU>
    </_-IWBEP_-I_SBO_PR>
    <_-IWBEP_-I_SBO_PR>
     <PROJECT>ZMM_METERIAL</PROJECT>
     <NODE_UUID>EpFVEf8BHuqnhQ1wji1k6w==</NODE_UUID>
     <PARENT_UUID>EpFVEf8BHuqnhQ1wjizE6w==</PARENT_UUID>
     <NAME>Ntgew</NAME>
     <PROP_PRECISION>13</PROP_PRECISION>
     <SCALE>3</SCALE>
     <EDM_CORE_TYPE>Edm.Decimal</EDM_CORE_TYPE>
     <REF_TYPE>T</REF_TYPE>
     <ABAP_FIELD>NTGEW</ABAP_FIELD>
     <AS_ETAG_XU>X</AS_ETAG_XU>
     <REQUIREFILTER_XU>X</REQUIREFILTER_XU>
     <UNIT_PROP_XU>X</UNIT_PROP_XU>
     <ABTY_XU>X</ABTY_XU>
     <SORT_ORDER>5</SORT_ORDER>
     <DESCRIPTION_XU>X</DESCRIPTION_XU>
    </_-IWBEP_-I_SBO_PR>
    <_-IWBEP_-I_SBO_PR>
     <PROJECT>ZMM_METERIAL</PROJECT>
     <NODE_UUID>EpFVEf8BHuqnhRPTmM9k/w==</NODE_UUID>
     <PARENT_UUID>EpFVEf8BHuqnhRPTmM9E/w==</PARENT_UUID>
     <NAME>Matnr</NAME>
     <IS_KEY>X</IS_KEY>
     <MAX_LENGTH>40</MAX_LENGTH>
     <EDM_CORE_TYPE>Edm.String</EDM_CORE_TYPE>
     <REF_TYPE>T</REF_TYPE>
     <ABAP_FIELD>MATNR</ABAP_FIELD>
     <AS_ETAG_XU>X</AS_ETAG_XU>
     <REQUIREFILTER_XU>X</REQUIREFILTER_XU>
     <UNIT_PROP_XU>X</UNIT_PROP_XU>
     <ABTY_XU>X</ABTY_XU>
     <SORT_ORDER>1</SORT_ORDER>
     <DESCRIPTION_XU>X</DESCRIPTION_XU>
    </_-IWBEP_-I_SBO_PR>
    <_-IWBEP_-I_SBO_PR>
     <PROJECT>ZMM_METERIAL</PROJECT>
     <NODE_UUID>EpFVEf8BHuqnhRPTmM+E/w==</NODE_UUID>
     <PARENT_UUID>EpFVEf8BHuqnhRPTmM9E/w==</PARENT_UUID>
     <NAME>Werks</NAME>
     <MAX_LENGTH>4</MAX_LENGTH>
     <EDM_CORE_TYPE>Edm.String</EDM_CORE_TYPE>
     <REF_TYPE>T</REF_TYPE>
     <ABAP_FIELD>WERKS</ABAP_FIELD>
     <AS_ETAG_XU>X</AS_ETAG_XU>
     <REQUIREFILTER_XU>X</REQUIREFILTER_XU>
     <UNIT_PROP_XU>X</UNIT_PROP_XU>
     <ABTY_XU>X</ABTY_XU>
     <SORT_ORDER>2</SORT_ORDER>
     <DESCRIPTION_XU>X</DESCRIPTION_XU>
    </_-IWBEP_-I_SBO_PR>
    <_-IWBEP_-I_SBO_PR>
     <PROJECT>ZMM_METERIAL</PROJECT>
     <NODE_UUID>EpFVEf8BHuqnhRPTmM+k/w==</NODE_UUID>
     <PARENT_UUID>EpFVEf8BHuqnhRPTmM9E/w==</PARENT_UUID>
     <NAME>Ekgrp</NAME>
     <MAX_LENGTH>3</MAX_LENGTH>
     <EDM_CORE_TYPE>Edm.String</EDM_CORE_TYPE>
     <REF_TYPE>T</REF_TYPE>
     <ABAP_FIELD>EKGRP</ABAP_FIELD>
     <AS_ETAG_XU>X</AS_ETAG_XU>
     <REQUIREFILTER_XU>X</REQUIREFILTER_XU>
     <UNIT_PROP_XU>X</UNIT_PROP_XU>
     <ABTY_XU>X</ABTY_XU>
     <SORT_ORDER>3</SORT_ORDER>
     <DESCRIPTION_XU>X</DESCRIPTION_XU>
    </_-IWBEP_-I_SBO_PR>
   </_-IWBEP_-I_SBO_PR>
   <_-IWBEP_-I_SBO_PRT>
    <_-IWBEP_-I_SBO_PRT>
     <SYLANGU>E</SYLANGU>
     <PROJECT>ZMM_METERIAL</PROJECT>
     <NODE_UUID>EpFVEf8BHuqnhQ1wjizk6w==</NODE_UUID>
     <PROP_LABEL>Material</PROP_LABEL>
    </_-IWBEP_-I_SBO_PRT>
    <_-IWBEP_-I_SBO_PRT>
     <SYLANGU>E</SYLANGU>
     <PROJECT>ZMM_METERIAL</PROJECT>
     <NODE_UUID>EpFVEf8BHuqnhQ1wji0E6w==</NODE_UUID>
     <PROP_LABEL>Material type</PROP_LABEL>
    </_-IWBEP_-I_SBO_PRT>
    <_-IWBEP_-I_SBO_PRT>
     <SYLANGU>E</SYLANGU>
     <PROJECT>ZMM_METERIAL</PROJECT>
     <NODE_UUID>EpFVEf8BHuqnhQ1wji0k6w==</NODE_UUID>
     <PROP_LABEL>Base Unit</PROP_LABEL>
    </_-IWBEP_-I_SBO_PRT>
    <_-IWBEP_-I_SBO_PRT>
     <SYLANGU>E</SYLANGU>
     <PROJECT>ZMM_METERIAL</PROJECT>
     <NODE_UUID>EpFVEf8BHuqnhQ1wji1E6w==</NODE_UUID>
     <PROP_LABEL>Gross weight</PROP_LABEL>
    </_-IWBEP_-I_SBO_PRT>
    <_-IWBEP_-I_SBO_PRT>
     <SYLANGU>E</SYLANGU>
     <PROJECT>ZMM_METERIAL</PROJECT>
     <NODE_UUID>EpFVEf8BHuqnhQ1wji1k6w==</NODE_UUID>
     <PROP_LABEL>Net weight</PROP_LABEL>
    </_-IWBEP_-I_SBO_PRT>
    <_-IWBEP_-I_SBO_PRT>
     <SYLANGU>E</SYLANGU>
     <PROJECT>ZMM_METERIAL</PROJECT>
     <NODE_UUID>EpFVEf8BHuqnhRPTmM9k/w==</NODE_UUID>
     <PROP_LABEL>Material</PROP_LABEL>
    </_-IWBEP_-I_SBO_PRT>
    <_-IWBEP_-I_SBO_PRT>
     <SYLANGU>E</SYLANGU>
     <PROJECT>ZMM_METERIAL</PROJECT>
     <NODE_UUID>EpFVEf8BHuqnhRPTmM+E/w==</NODE_UUID>
     <PROP_LABEL>Plant</PROP_LABEL>
    </_-IWBEP_-I_SBO_PRT>
    <_-IWBEP_-I_SBO_PRT>
     <SYLANGU>E</SYLANGU>
     <PROJECT>ZMM_METERIAL</PROJECT>
     <NODE_UUID>EpFVEf8BHuqnhRPTmM+k/w==</NODE_UUID>
     <PROP_LABEL>Purch. Group</PROP_LABEL>
    </_-IWBEP_-I_SBO_PRT>
   </_-IWBEP_-I_SBO_PRT>
   <_-IWBEP_-I_SBO_RC>
    <_-IWBEP_-I_SBO_RC>
     <PROJECT>ZMM_METERIAL</PROJECT>
     <NODE_UUID>EpFVEf8BHuqnhRskqCuFAw==</NODE_UUID>
     <NAME>Matnr</NAME>
     <DEPENDENT_PROP_R>EpFVEf8BHuqnhRPTmM9k/w==</DEPENDENT_PROP_R>
     <PRINCIPAL_PROP_R>EpFVEf8BHuqnhQ1wjizk6w==</PRINCIPAL_PROP_R>
     <PRINCIPAL_ROLE>EpFVEf8BHuqnhQ1wjizE6w==</PRINCIPAL_ROLE>
     <DEPENDENT_ROLE>EpFVEf8BHuqnhRPTmM9E/w==</DEPENDENT_ROLE>
     <ASSOCIATION_GUID>EpFVEf8BHuqnhRskqCtFAw==</ASSOCIATION_GUID>
     <REF_TYPE>T</REF_TYPE>
     <TXTR_XU>X</TXTR_XU>
     <DESCRIPTION_XU>X</DESCRIPTION_XU>
     <REFC_LABEL_XU>X</REFC_LABEL_XU>
     <PROPERTY_PATH>00000000000000000000000000000000</PROPERTY_PATH>
     <REF_PROP_PATH>00000000000000000000000000000000</REF_PROP_PATH>
    </_-IWBEP_-I_SBO_RC>
   </_-IWBEP_-I_SBO_RC>
   <_-IWBEP_-I_SBO_RCT>
    <_-IWBEP_-I_SBO_RCT>
     <SYLANGU>E</SYLANGU>
     <PROJECT>ZMM_METERIAL</PROJECT>
     <NODE_UUID>EpFVEf8BHuqnhRskqCuFAw==</NODE_UUID>
    </_-IWBEP_-I_SBO_RCT>
   </_-IWBEP_-I_SBO_RCT>
  </asx:values>
 </asx:abap>
</abapGit>
